json_cfg-0.4.2.dist-info/DESCRIPTION.rst
json_cfg-0.4.2.dist-info/METADATA
json_cfg-0.4.2.dist-info/RECORD
json_cfg-0.4.2.dist-info/WHEEL
json_cfg-0.4.2.dist-info/metadata.json
json_cfg-0.4.2.dist-info/top_level.txt
jsoncfg/__init__.py
jsoncfg/compatibility.py
jsoncfg/config_classes.py
jsoncfg/exceptions.py
jsoncfg/functions.py
jsoncfg/parser.py
jsoncfg/parser_listener.py
jsoncfg/text_encoding.py
jsoncfg/tree_config.py
jsoncfg/tree_python.py
jsoncfg/value_mappers.py
