Metadata-Version: 2.0
Name: json-cfg
Version: 0.4.2
Summary: JSON config file parser with extended syntax (e.g.: comments), line/column numbers in error messages, etc...
Home-page: https://github.com/pasztorpisti/json-cfg
Author: István Pásztor
Author-email: pasztorpisti@gmail.com
License: MIT
Keywords: json config file parser configuration comment
Platform: UNKNOWN
Classifier: License :: OSI Approved :: MIT License
Classifier: Development Status :: 4 - Beta
Classifier: Intended Audience :: Developers
Classifier: Topic :: Software Development :: Libraries :: Python Modules
Classifier: Programming Language :: Python :: 2
Classifier: Programming Language :: Python :: 2.7
Classifier: Programming Language :: Python :: 3
Classifier: Programming Language :: Python :: 3.3
Classifier: Programming Language :: Python :: 3.4
Classifier: Programming Language :: Python :: 3.5
Classifier: Programming Language :: Python :: Implementation :: CPython
Classifier: Programming Language :: Python :: Implementation :: PyPy
Requires-Dist: kwonly-args (>=1.0.7)
